{"id":"battle-gen9championsvgc2026regmb-2635034274","v":"0.13.0","t":"2026-06-19T07:51:45.745261+00:00","outcome":"win","team":"meta-team","team_version":"v1","preview":{"opp":["Greninja","Ninetales-Alola","Metagross","Incineroar","Whimsicott","Mamoswine"],"slots":[5,3,2,6],"bring":["Venusaur","Sneasler","Kingambit","Garchomp"],"mega":"Venusaur"},"turns":[{"n":1,"my":[{"s":"Venusaur","hp":1.0},{"s":"Sneasler","hp":1.0}],"opp":[{"s":"Ninetales-Alola","hp":1.0},{"s":"Whimsicott","hp":1.0}],"team":[{"s":"Venusaur","hp":1.0},{"s":"Sneasler","hp":1.0},{"s":"Kingambit","hp":1.0},{"s":"Garchomp","hp":1.0}],"dec":[{"sl":0,"ch":"Sludge Bomb","acts":[{"lb":"Sludge Bomb","w":12.47,"ts":1,"tg":"Whimsicott","r":["damage_output: 302% HP -> x11.09","turn_order: turn order pos 4/4 (beat 0/3) -> x0.75","tailwind: TW setter on field (TW not active) -> x1.5","doubling_up: both attack slot 1 -> x0.55"]},{"lb":"Sludge Bomb","w":4.93,"ts":0,"tg":"Ninetales-Alola","r":["damage_output: 111% HP -> x4.38","turn_order: turn order pos 4/4 (beat 0/3) -> x0.75","tailwind: TW setter on field (TW not active) -> x1.5"]},{"lb":"Giga Drain","w":2.38,"ts":0,"tg":"Ninetales-Alola","r":["damage_output: 46% HP -> x2.12","turn_order: turn order pos 4/4 (beat 0/3) -> x0.75","tailwind: TW setter on field (TW not active) -> x1.5"]},{"lb":"Earth Power","w":2.02,"ts":0,"tg":"Ninetales-Alola","r":["damage_output: 37% HP -> x1.79","turn_order: turn order pos 4/4 (beat 0/3) -> x0.75","tailwind: TW setter on field (TW not active) -> x1.5"]}],"ct":"Whimsicott"},{"sl":1,"ch":"Dire Claw","acts":[{"lb":"Dire Claw","w":6.57,"ts":1,"tg":"Whimsicott","r":["damage_output: 213% HP -> x7.97","turn_order: turn order pos 3/4 (beat 1/3) -> x1.0","tailwind: TW setter on field (TW not active) -> x1.5","doubling_up: both attack slot 1 -> x0.55"]},{"lb":"Dire Claw","w":6.45,"ts":0,"tg":"Ninetales-Alola","r":["damage_output: 109% HP -> x4.30","turn_order: turn order pos 3/4 (beat 1/3) -> x1.0","tailwind: TW setter on field (TW not active) -> x1.5"]},{"lb":"Close Combat","w":5.02,"ts":0,"tg":"Ninetales-Alola","r":["damage_output: 81% HP -> x3.35","turn_order: turn order pos 3/4 (beat 1/3) -> x1.0","tailwind: TW setter on field (TW not active) -> x1.5"]},{"lb":"Rock Tomb","w":3.66,"ts":0,"tg":"Ninetales-Alola","r":["damage_output: 56% HP -> x2.44","turn_order: turn order pos 3/4 (beat 1/3) -> x1.0","tailwind: TW setter on field (TW not active) -> x1.5"]}],"ct":"Whimsicott"}],"ev":[{"o":0,"sd":"opp","a":"Whimsicott","mv":"Tailwind","tg":"Whimsicott","h0":1.0},{"o":1,"sd":"opp","a":"Ninetales-Alola","mv":"Aurora Veil","tg":"Ninetales-Alola","h0":1.0},{"o":2,"sd":"us","a":"Sneasler","mv":"Dire Claw","tg":"Whimsicott","h0":1.0,"d":0.87},{"o":3,"sd":"us","a":"Venusaur-Mega","mv":"Sludge Bomb","tg":"Whimsicott","h0":0.13,"d":0.13}],"pin":[{"a":"Ninetales-Alola","df":"Venusaur","mvs":{"Blizzard":0.257,"Freeze-Dry":0.228,"Moonblast":0.148}},{"a":"Whimsicott","df":"Venusaur","mvs":{"Moonblast":0.148}},{"a":"Ninetales-Alola","df":"Sneasler","mvs":{"Moonblast":0.42,"Blizzard":0.361,"Freeze-Dry":0.312}},{"a":"Whimsicott","df":"Sneasler","mvs":{"Moonblast":0.406}}]},{"n":2,"tw":{"us":false,"opp":true},"my":[{"s":"Venusaur-Mega","hp":1.0},{"s":"Sneasler","hp":1.0}],"opp":[{"s":"Ninetales-Alola","hp":1.0,"mv":["Aurora Veil"]},{"s":"Metagross","hp":1.0}],"team":[{"s":"Venusaur-Mega","hp":1.0},{"s":"Sneasler","hp":1.0},{"s":"Kingambit","hp":1.0},{"s":"Garchomp","hp":1.0}],"dec":[{"sl":0,"ch":"Switch Kingambit","acts":[{"lb":"Switch Kingambit","w":8.73,"sw":"Kingambit","r":["switch_eval: tempo -> x0.8","switch_eval: +173% offense gain -> x2.73","switch_eval: escapes OHKO -> x4.0"]},{"lb":"Protect","w":7.5,"r":["incoming_ohko: OHKO threat -> x2.5","field_condition: 3rd-to-last turn of opp Tailwind -> x3.0"]},{"lb":"Sludge Bomb","w":2.32,"ts":0,"tg":"Ninetales-Alola","r":["damage_output: 74% HP -> x3.09","turn_order: turn order pos 4/4 (beat 0/3) -> x0.75"]},{"lb":"Earth Power","w":1.51,"ts":1,"tg":"Metagross","r":["damage_output: 43% HP -> x2.01","turn_order: turn order pos 4/4 (beat 0/3) -> x0.75"]}]},{"sl":1,"ch":"Switch Kingambit","acts":[{"lb":"Switch Kingambit","w":8.8,"sw":"Kingambit","r":["switch_eval: tempo -> x0.8","switch_eval: +175% offense gain -> x2.75","switch_eval: escapes OHKO -> x4.0"]},{"lb":"Protect","w":7.5,"r":["incoming_ohko: OHKO threat -> x2.5","field_condition: 3rd-to-last turn of opp Tailwind -> x3.0"]},{"lb":"Dire Claw","w":3.03,"ts":0,"tg":"Ninetales-Alola","r":["damage_output: 72% HP -> x3.03","turn_order: turn order pos 3/4 (beat 1/3) -> x1.0"]},{"lb":"Close Combat","w":2.4,"ts":0,"tg":"Ninetales-Alola","r":["damage_output: 54% HP -> x2.40","turn_order: turn order pos 3/4 (beat 1/3) -> x1.0"]}]}],"ev":[{"o":0,"sd":"us","a":"Venusaur-Mega","mv":"Protect","tg":"Venusaur-Mega","h0":1.0},{"o":1,"sd":"opp","a":"Metagross-Mega","mv":"Psychic Fangs","tg":"Venusaur-Mega","h0":1.0,"z":"protect"},{"o":2,"sd":"opp","a":"Ninetales-Alola","mv":"Dazzling Gleam","tg":"Kingambit","h0":1.0,"d":0.16,"z":"protect"}],"pin":[{"a":"Ninetales-Alola","df":"Venusaur-Mega","mvs":{"Blizzard":0.257,"Freeze-Dry":0.228,"Moonblast":0.148}},{"a":"Metagross","df":"Venusaur-Mega","mvs":{"Psychic Fangs":1.049,"Meteor Mash":0.554,"Iron Head":0.495,"Stomping Tantrum":0.312,"Bullet Punch":0.252}},{"a":"Ninetales-Alola","df":"Sneasler","mvs":{"Moonblast":0.42,"Blizzard":0.361,"Freeze-Dry":0.312}},{"a":"Metagross","df":"Sneasler","mvs":{"Psychic Fangs":3.284,"Stomping Tantrum":0.97,"Meteor Mash":0.866,"Iron Head":0.772,"Bullet Punch":0.391}}]},{"n":3,"tw":{"us":false,"opp":true},"my":[{"s":"Venusaur-Mega","hp":1.0},{"s":"Kingambit","hp":0.84}],"opp":[{"s":"Ninetales-Alola","hp":1.0,"mv":["Aurora Veil","Dazzling Gleam"]},{"s":"Metagross-Mega","hp":1.0,"mv":["Psychic Fangs"]}],"team":[{"s":"Venusaur-Mega","hp":1.0},{"s":"Kingambit","hp":0.84},{"s":"Sneasler","hp":1.0},{"s":"Garchomp","hp":1.0}],"dec":[{"sl":0,"ch":"Sludge Bomb","acts":[{"lb":"Sludge Bomb","w":3.09,"ts":0,"tg":"Ninetales-Alola","r":["damage_output: 74% HP -> x3.09","turn_order: turn order pos 3/4 (beat 1/3) -> x1.0"]},{"lb":"Earth Power","w":2.01,"ts":1,"tg":"Metagross-Mega","r":["damage_output: 43% HP -> x2.01","turn_order: turn order pos 3/4 (beat 1/3) -> x1.0"]},{"lb":"Giga Drain","w":1.58,"ts":0,"tg":"Ninetales-Alola","r":["damage_output: 31% HP -> x1.58","turn_order: turn order pos 3/4 (beat 1/3) -> x1.0"]},{"lb":"Earth Power","w":1.36,"ts":0,"tg":"Ninetales-Alola","r":["damage_output: 25% HP -> x1.36","turn_order: turn order pos 3/4 (beat 1/3) -> x1.0"]},{"lb":"Protect","w":0.5,"r":["incoming_ohko: OHKO threat -> x2.5","consecutive_protect: used Protect last turn -> x0.2"]}],"ct":"Ninetales-Alola"},{"sl":1,"ch":"Iron Head","acts":[{"lb":"Iron Head","w":5.34,"ts":0,"tg":"Ninetales-Alola","r":["damage_output: 189% HP -> x7.12","turn_order: turn order pos 4/4 (beat 0/3) -> x0.75"]},{"lb":"Kowtow Cleave","w":1.82,"ts":1,"tg":"Metagross-Mega","r":["damage_output: 55% HP -> x2.42","turn_order: turn order pos 4/4 (beat 0/3) -> x0.75"]},{"lb":"Low Kick","w":1.05,"ts":1,"tg":"Metagross-Mega","r":["damage_output: 26% HP -> x1.39","turn_order: turn order pos 4/4 (beat 0/3) -> x0.75"]},{"lb":"Kowtow Cleave","w":1.03,"ts":0,"tg":"Ninetales-Alola","r":["damage_output: 25% HP -> x1.38","turn_order: turn order pos 4/4 (beat 0/3) -> x0.75"]}],"ct":"Ninetales-Alola"}],"ev":[{"o":0,"sd":"opp","a":"Metagross-Mega","mv":"Protect","tg":"Metagross-Mega","h0":1.0},{"o":1,"sd":"us","a":"Venusaur-Mega","mv":"Earth Power","tg":"Metagross-Mega","h0":1.0,"z":"protect"},{"o":2,"sd":"us","a":"Kingambit","mv":"Iron Head","tg":"Mamoswine","h0":1.0,"d":1.0,"cr":true}],"pin":[{"a":"Ninetales-Alola","df":"Venusaur-Mega","mvs":{"Blizzard":0.257,"Freeze-Dry":0.228,"Moonblast":0.148}},{"a":"Metagross-Mega","df":"Venusaur-Mega","mvs":{"Psychic Fangs":1.049,"Meteor Mash":0.554,"Iron Head":0.495,"Stomping Tantrum":0.312,"Bullet Punch":0.252}},{"a":"Ninetales-Alola","df":"Kingambit","mvs":{"Moonblast":0.364,"Blizzard":0.157,"Freeze-Dry":0.135}},{"a":"Metagross-Mega","df":"Kingambit","mvs":{"Stomping Tantrum":0.611,"Meteor Mash":0.269,"Iron Head":0.242,"Bullet Punch":0.121,"Psychic Fangs":0.0}}]},{"n":4,"tw":{"us":false,"opp":true},"my":[{"s":"Venusaur-Mega","hp":1.0},{"s":"Kingambit","hp":0.84}],"opp":[{"s":"Ninetales-Alola","hp":1.0},{"s":"Metagross-Mega","hp":1.0,"mv":["Protect","Psychic Fangs"]}],"team":[{"s":"Venusaur-Mega","hp":1.0},{"s":"Kingambit","hp":0.84},{"s":"Sneasler","hp":1.0},{"s":"Garchomp","hp":1.0}],"dec":[{"sl":0,"ch":"Protect","acts":[{"lb":"Protect","w":7.5,"r":["incoming_ohko: OHKO threat -> x2.5","field_condition: last turn of opp Tailwind -> x3.0"]},{"lb":"Sludge Bomb","w":3.09,"ts":0,"tg":"Ninetales-Alola","r":["damage_output: 74% HP -> x3.09","turn_order: turn order pos 3/4 (beat 1/3) -> x1.0"]},{"lb":"Earth Power","w":2.62,"ts":1,"tg":"Metagross-Mega","r":["damage_output: 43% HP -> x2.01","turn_order: turn order pos 3/4 (beat 1/3) -> x1.0","opp_protect_recency: target used Protect last turn -> x1.3"]},{"lb":"Giga Drain","w":1.58,"ts":0,"tg":"Ninetales-Alola","r":["damage_output: 31% HP -> x1.58","turn_order: turn order pos 3/4 (beat 1/3) -> x1.0"]}]},{"sl":1,"ch":"Iron Head","acts":[{"lb":"Iron Head","w":5.34,"ts":0,"tg":"Ninetales-Alola","r":["damage_output: 189% HP -> x7.12","turn_order: turn order pos 4/4 (beat 0/3) -> x0.75"]},{"lb":"Protect","w":3.0,"r":["field_condition: last turn of opp Tailwind -> x3.0"]},{"lb":"Kowtow Cleave","w":2.36,"ts":1,"tg":"Metagross-Mega","r":["damage_output: 55% HP -> x2.42","turn_order: turn order pos 4/4 (beat 0/3) -> x0.75","opp_protect_recency: target used Protect last turn -> x1.3"]},{"lb":"Low Kick","w":1.36,"ts":1,"tg":"Metagross-Mega","r":["damage_output: 26% HP -> x1.39","turn_order: turn order pos 4/4 (beat 0/3) -> x0.75","opp_protect_recency: target used Protect last turn -> x1.3"]}],"ct":"Ninetales-Alola"}],"ev":[{"o":0,"sd":"us","a":"Venusaur-Mega","mv":"Protect","tg":"Venusaur-Mega","h0":1.0},{"o":1,"sd":"opp","a":"Metagross-Mega","mv":"Psychic Fangs","tg":"Venusaur-Mega","h0":1.0,"z":"protect"},{"o":2,"sd":"opp","a":"Ninetales-Alola","mv":"Freeze-Dry","tg":"Kingambit","h0":0.84,"d":0.107},{"o":3,"sd":"us","a":"Kingambit","mv":"Iron Head","tg":"Ninetales-Alola","h0":1.0,"d":1.0}],"pin":[{"a":"Ninetales-Alola","df":"Venusaur-Mega","mvs":{"Blizzard":0.257,"Freeze-Dry":0.228,"Moonblast":0.148}},{"a":"Metagross-Mega","df":"Venusaur-Mega","mvs":{"Psychic Fangs":1.049,"Meteor Mash":0.554,"Iron Head":0.495,"Stomping Tantrum":0.312,"Bullet Punch":0.252}},{"a":"Ninetales-Alola","df":"Kingambit","mvs":{"Moonblast":0.364,"Blizzard":0.157,"Freeze-Dry":0.135}},{"a":"Metagross-Mega","df":"Kingambit","mvs":{"Stomping Tantrum":0.611,"Meteor Mash":0.269,"Iron Head":0.242,"Bullet Punch":0.121,"Psychic Fangs":0.0}}]},{"n":5,"my":[{"s":"Venusaur-Mega","hp":1.0},{"s":"Kingambit","hp":0.733}],"opp":[{"s":"Ninetales-Alola","hp":0.0,"mv":["Freeze-Dry"]},{"s":"Metagross-Mega","hp":1.0,"mv":["Protect","Psychic Fangs"]}],"team":[{"s":"Venusaur-Mega","hp":1.0},{"s":"Kingambit","hp":0.733},{"s":"Sneasler","hp":1.0},{"s":"Garchomp","hp":1.0}],"dec":[{"sl":0,"ch":"Switch Garchomp","acts":[{"lb":"Switch Garchomp","w":3.39,"sw":"Garchomp","r":["switch_eval: tempo -> x0.8","switch_eval: +6% offense gain -> x1.06","switch_eval: escapes OHKO -> x4.0"]},{"lb":"Earth Power","w":3.02,"ts":1,"tg":"Metagross-Mega","r":["damage_output: 43% HP -> x2.01","turn_order: turn order pos 2/3 (beat 1/2) -> x1.5"]},{"lb":"Giga Drain","w":1.45,"ts":1,"tg":"Metagross-Mega","r":["damage_output: 13% HP -> x0.97","turn_order: turn order pos 2/3 (beat 1/2) -> x1.5"]},{"lb":"Protect","w":0.2,"r":["incoming_ohko: OHKO threat -> x2.5","incoming_ohko: 2v1 advantage, Protect can't improve the outcome -> x0.4","consecutive_protect: used Protect last turn -> x0.2"]}]},{"sl":1,"ch":"Kowtow Cleave","acts":[{"lb":"Kowtow Cleave","w":2.42,"ts":1,"tg":"Metagross-Mega","r":["damage_output: 55% HP -> x2.42","turn_order: turn order pos 3/3 (beat 0/2) -> x1.0"]},{"lb":"Low Kick","w":1.39,"ts":1,"tg":"Metagross-Mega","r":["damage_output: 26% HP -> x1.39","turn_order: turn order pos 3/3 (beat 0/2) -> x1.0"]},{"lb":"Protect","w":1.0}],"ct":"Metagross-Mega"}],"ev":[{"o":0,"sd":"opp","a":"Metagross-Mega","mv":"Psychic Fangs","tg":"Garchomp","h0":1.0,"d":0.574},{"o":1,"sd":"us","a":"Kingambit","mv":"Kowtow Cleave","tg":"Metagross-Mega","h0":0.87,"d":0.51}],"pin":[{"a":"Metagross-Mega","df":"Venusaur-Mega","mvs":{"Psychic Fangs":1.049,"Meteor Mash":0.554,"Iron Head":0.495,"Stomping Tantrum":0.312,"Bullet Punch":0.252}},{"a":"Metagross-Mega","df":"Kingambit","mvs":{"Stomping Tantrum":0.611,"Meteor Mash":0.269,"Iron Head":0.242,"Bullet Punch":0.121,"Psychic Fangs":0.0}}]},{"n":6,"my":[{"s":"Garchomp","hp":0.426},{"s":"Kingambit","hp":0.733}],"opp":[{"s":"Ninetales-Alola","hp":0.0,"mv":["Freeze-Dry"]},{"s":"Metagross-Mega","hp":0.36,"mv":["Protect","Psychic Fangs"]}],"team":[{"s":"Garchomp","hp":0.426},{"s":"Kingambit","hp":0.733},{"s":"Sneasler","hp":1.0},{"s":"Venusaur-Mega","hp":1.0}],"dec":[{"sl":0,"ch":"Stomping Tantrum","acts":[{"lb":"Stomping Tantrum","w":54.87,"ts":1,"tg":"Metagross-Mega","r":["damage_output: 195% HP -> x7.32","threat_elimination: guaranteed OHKO on Metagross-Mega -> x5.0","turn_order: turn order pos 2/3 (beat 1/2) -> x1.5"]},{"lb":"Dragon Claw","w":3.48,"ts":1,"tg":"Metagross-Mega","r":["damage_output: 52% HP -> x2.32","turn_order: turn order pos 2/3 (beat 1/2) -> x1.5"]},{"lb":"Rock Tomb","w":2.11,"ts":1,"tg":"Metagross-Mega","r":["damage_output: 26% HP -> x1.41","turn_order: turn order pos 2/3 (beat 1/2) -> x1.5"]}],"ct":"Metagross-Mega"},{"sl":1,"ch":"Kowtow Cleave","acts":[{"lb":"Kowtow Cleave","w":42.26,"ts":1,"tg":"Metagross-Mega","r":["damage_output: 227% HP -> x8.45","threat_elimination: guaranteed OHKO on Metagross-Mega -> x5.0","turn_order: turn order pos 3/3 (beat 0/2) -> x1.0"]},{"lb":"Low Kick","w":4.19,"ts":1,"tg":"Metagross-Mega","r":["damage_output: 105% HP -> x4.19","turn_order: turn order pos 3/3 (beat 0/2) -> x1.0"]},{"lb":"Iron Head","w":2.37,"ts":1,"tg":"Metagross-Mega","r":["damage_output: 54% HP -> x2.37","turn_order: turn order pos 3/3 (beat 0/2) -> x1.0"]}],"ct":"Metagross-Mega"}],"ev":[{"o":0,"sd":"us","a":"Garchomp","mv":"Stomping Tantrum","tg":"Metagross-Mega","h0":0.36,"d":0.36}],"pin":[{"a":"Metagross-Mega","df":"Garchomp","mvs":{"Meteor Mash":0.723,"Psychic Fangs":0.684,"Iron Head":0.64,"Stomping Tantrum":0.403,"Bullet Punch":0.325}},{"a":"Metagross-Mega","df":"Kingambit","mvs":{"Stomping Tantrum":0.611,"Meteor Mash":0.269,"Iron Head":0.242,"Bullet Punch":0.121,"Psychic Fangs":0.0}}]}]}