{"id":"battle-gen9championsvgc2026regmb-2640619186","v":"0.36.0","t":"2026-06-28T16:17:02.176648+00:00","outcome":"loss","team":"meta-team","team_version":"v8","preview":{"opp":["Grimmsnarl","Eelektross","Medicham","Mamoswine","Espathra","Clefable"],"slots":[2,3,4,5],"bring":["Kingambit","Basculegion","Ceruledge","Decidueye-Hisui"],"pred":["Grimmsnarl","Mamoswine"]},"final":{"my":[{"s":"Decidueye-Hisui","hp":0.0},{"s":"Ceruledge","hp":0.0}],"opp":[{"s":"Eelektross-Mega","hp":0.55,"mv":["Discharge","Flamethrower","Giga Drain"],"b":{"spa":3}},{"s":"Clefable","hp":0.58,"mv":["Follow Me","Protect","Psych Up"]}],"team":[{"s":"Decidueye-Hisui","hp":0.0},{"s":"Ceruledge","hp":0.0},{"s":"Kingambit","hp":0.0},{"s":"Basculegion","hp":0.0}]},"opp_formes":["Clefable","Eelektross","Eelektross-Mega","Espathra","Grimmsnarl"],"turns":[{"n":1,"my":[{"s":"Kingambit","hp":1.0},{"s":"Basculegion","hp":1.0}],"opp":[{"s":"Espathra","hp":1.0},{"s":"Grimmsnarl","hp":1.0}],"team":[{"s":"Kingambit","hp":1.0},{"s":"Basculegion","hp":1.0},{"s":"Ceruledge","hp":1.0},{"s":"Decidueye-Hisui","hp":1.0}],"dec":[{"sl":0,"ch":"Sucker Punch","acts":[{"lb":"Sucker Punch","w":3.0,"ts":0,"tg":"Espathra","r":["damage_output: 129% HP -> x4.00 (overkill capped)","turn_order: turn order pos 4/4 (beat 0/3) -> x0.75"]},{"lb":"Kowtow Cleave","w":3.0,"ts":0,"tg":"Espathra","r":["damage_output: 156% HP -> x4.00 (overkill capped)","turn_order: turn order pos 4/4 (beat 0/3) -> x0.75"]},{"lb":"Iron Head","w":2.92,"ts":1,"tg":"Grimmsnarl","r":["damage_output: 97% HP -> x3.90","turn_order: turn order pos 4/4 (beat 0/3) -> x0.75"]},{"lb":"Iron Head","w":2.32,"ts":0,"tg":"Espathra","r":["damage_output: 74% HP -> x3.10","turn_order: turn order pos 4/4 (beat 0/3) -> x0.75"]}],"wall":{"Sucker Punch>0":3.0,"Kowtow Cleave>0":3.0,"Iron Head>1":2.92,"Iron Head>0":2.32,"Protect":1.0,"+Ceruledge":0.82,"+Decidueye-Hisui":0.8,"Kowtow Cleave>1":0.71,"Sucker Punch>1":0.65},"ct":"Espathra"},{"sl":1,"ch":"Last Respects","acts":[{"lb":"Last Respects","w":8.0,"ts":0,"tg":"Espathra","r":["damage_output: 101% HP -> x4.00 (overkill capped)","turn_order: turn order pos 1/4 (beat 3/3) -> x2.0"]},{"lb":"Wave Crash","w":8.0,"ts":0,"tg":"Espathra","r":["damage_output: 118% HP -> x4.00 (overkill capped)","turn_order: turn order pos 1/4 (beat 3/3) -> x2.0"]},{"lb":"Wave Crash","w":6.45,"ts":1,"tg":"Grimmsnarl","r":["damage_output: 78% HP -> x3.22","turn_order: turn order pos 1/4 (beat 3/3) -> x2.0"]},{"lb":"Aqua Jet","w":3.86,"ts":0,"tg":"Espathra","r":["damage_output: 41% HP -> x1.93","turn_order: turn order pos 1/4 (beat 3/3) -> x2.0"]}],"wall":{"Last Respects>0":8.0,"Wave Crash>0":8.0,"Wave Crash>1":6.45,"Aqua Jet>0":3.86,"Aqua Jet>1":2.86,"Psychic Fangs>0":2.47,"Last Respects>1":2.15,"+Ceruledge":1.12,"Psychic Fangs>1":1.0,"+Decidueye-Hisui":0.8},"ct":"Espathra"}],"ev":[{"o":0,"sd":"opp","a":"Grimmsnarl","mv":"Fake Out","tg":"Kingambit","h0":1.0,"d":0.043},{"o":1,"sd":"us","a":"Basculegion","mv":"Last Respects","tg":"Espathra","h0":1.0,"d":0.55},{"o":2,"sd":"opp","a":"Espathra","mv":"Calm Mind","tg":"Espathra","h0":0.45}],"pin":[{"a":"Espathra","df":"Kingambit","mvs":{"Dazzling Gleam":0.174,"Lumina Crash":0.0}},{"a":"Grimmsnarl","df":"Kingambit","mvs":{"Spirit Break":0.232,"Fake Out":0.04}},{"a":"Espathra","df":"Basculegion","mvs":{"Lumina Crash":0.409,"Dazzling Gleam":0.202}},{"a":"Grimmsnarl","df":"Basculegion","mvs":{"Spirit Break":0.394,"Fake Out":0.0}}]},{"n":2,"my":[{"s":"Kingambit","hp":0.957},{"s":"Basculegion","hp":1.0}],"opp":[{"s":"Espathra","hp":0.51,"mv":["Calm Mind"],"b":{"spa":1,"spd":1,"spe":1}},{"s":"Grimmsnarl","hp":1.0,"mv":["Fake Out"]}],"team":[{"s":"Kingambit","hp":0.957},{"s":"Basculegion","hp":1.0},{"s":"Ceruledge","hp":1.0},{"s":"Decidueye-Hisui","hp":1.0}],"dec":[{"sl":0,"ch":"Sucker Punch","acts":[{"lb":"Sucker Punch","w":45.0,"ts":0,"tg":"Espathra","r":["damage_output: 252% HP -> x4.00 (overkill capped)","threat_elimination: guaranteed OHKO on Espathra -> x5.0","priority_kill: priority move guarantees a kill -> x3.0","turn_order: turn order pos 4/4 (beat 0/3) -> x0.75"]},{"lb":"Kowtow Cleave","w":15.0,"ts":0,"tg":"Espathra","r":["damage_output: 305% HP -> x4.00 (overkill capped)","threat_elimination: guaranteed OHKO on Espathra -> x5.0","turn_order: turn order pos 4/4 (beat 0/3) -> x0.75"]},{"lb":"Iron Head","w":15.0,"ts":0,"tg":"Espathra","r":["damage_output: 145% HP -> x4.00 (overkill capped)","threat_elimination: guaranteed OHKO on Espathra -> x5.0","turn_order: turn order pos 4/4 (beat 0/3) -> x0.75"]},{"lb":"Iron Head","w":2.92,"ts":1,"tg":"Grimmsnarl","r":["damage_output: 97% HP -> x3.90","turn_order: turn order pos 4/4 (beat 0/3) -> x0.75"]}],"wall":{"Sucker Punch>0":45.0,"Kowtow Cleave>0":15.0,"Iron Head>0":15.0,"Iron Head>1":2.92,"Protect":1.0,"+Ceruledge":0.83,"Kowtow Cleave>1":0.71,"Sucker Punch>1":0.65,"+Decidueye-Hisui":0.24},"ct":"Espathra"},{"sl":1,"ch":"Last Respects","acts":[{"lb":"Last Respects","w":30.0,"ts":0,"tg":"Espathra","r":["damage_output: 198% HP -> x4.00 (overkill capped)","threat_elimination: guaranteed OHKO on Espathra -> x5.0","turn_order: turn order pos 2/4 (beat 2/3) -> x1.5"]},{"lb":"Switch Ceruledge","w":1.69,"sw":"Ceruledge","r":["switch_tempo: tempo -> x0.8","switch_offense: +111% offense gain -> x2.11"]},{"lb":"Last Respects","w":1.62,"ts":1,"tg":"Grimmsnarl","r":["damage_output: 16% HP -> x1.08","turn_order: turn order pos 2/4 (beat 2/3) -> x1.5"]}],"wall":{"Last Respects>0":30.0,"+Ceruledge":1.69,"Last Respects>1":1.62,"+Decidueye-Hisui":0.24},"ct":"Espathra"}],"ev":[{"o":0,"sd":"opp","a":"Espathra","mv":"Protect","tg":"Espathra","h0":0.51},{"o":1,"sd":"opp","a":"Grimmsnarl","mv":"Reflect","tg":"Grimmsnarl","h0":1.0},{"o":2,"sd":"us","a":"Basculegion","mv":"Last Respects","tg":"Espathra","h0":0.51,"z":"protect"},{"o":3,"sd":"us","a":"Kingambit","mv":"Iron Head","tg":"Grimmsnarl","h0":1.0,"d":0.74}],"pin":[{"a":"Espathra","df":"Kingambit","mvs":{"Dazzling Gleam":0.266,"Lumina Crash":0.0}},{"a":"Grimmsnarl","df":"Kingambit","mvs":{"Spirit Break":0.243,"Fake Out":0.042}},{"a":"Espathra","df":"Basculegion","mvs":{"Lumina Crash":0.606,"Dazzling Gleam":0.301}},{"a":"Grimmsnarl","df":"Basculegion","mvs":{"Spirit Break":0.394,"Fake Out":0.0}}]},{"n":3,"my":[{"s":"Kingambit","hp":0.957},{"s":"Basculegion","hp":1.0}],"opp":[{"s":"Espathra","hp":0.57,"mv":["Calm Mind","Protect"],"b":{"spa":1,"spd":1,"spe":2}},{"s":"Grimmsnarl","hp":0.26,"mv":["Fake Out","Reflect"]}],"team":[{"s":"Kingambit","hp":0.957},{"s":"Basculegion","hp":1.0},{"s":"Ceruledge","hp":1.0},{"s":"Decidueye-Hisui","hp":1.0}],"dec":[{"sl":0,"ch":"Sucker Punch","acts":[{"lb":"Sucker Punch","w":58.5,"ts":0,"tg":"Espathra","r":["damage_output: 151% HP -> x4.00 (overkill capped)","threat_elimination: guaranteed OHKO on Espathra -> x5.0","priority_kill: priority move guarantees a kill -> x3.0","turn_order: turn order pos 4/4 (beat 0/3) -> x0.75","opp_protect_recency: target used Protect last turn -> x1.3"]},{"lb":"Kowtow Cleave","w":19.5,"ts":0,"tg":"Espathra","r":["damage_output: 182% HP -> x4.00 (overkill capped)","threat_elimination: guaranteed OHKO on Espathra -> x5.0","turn_order: turn order pos 4/4 (beat 0/3) -> x0.75","opp_protect_recency: target used Protect last turn -> x1.3"]},{"lb":"Iron Head","w":15.0,"ts":1,"tg":"Grimmsnarl","r":["damage_output: 247% HP -> x4.00 (overkill capped)","threat_elimination: guaranteed OHKO on Grimmsnarl -> x5.0","turn_order: turn order pos 4/4 (beat 0/3) -> x0.75"]},{"lb":"Iron Head","w":3.45,"ts":0,"tg":"Espathra","r":["damage_output: 87% HP -> x3.54","turn_order: turn order pos 4/4 (beat 0/3) -> x0.75","opp_protect_recency: target used Protect last turn -> x1.3"]}],"wall":{"Sucker Punch>0":58.5,"Kowtow Cleave>0":19.5,"Iron Head>1":15.0,"Iron Head>0":3.45,"Kowtow Cleave>1":1.23,"Sucker Punch>1":1.08,"Protect":1.0,"+Ceruledge":0.8,"+Decidueye-Hisui":0.24},"ct":"Espathra"},{"sl":1,"ch":"Last Respects","acts":[{"lb":"Last Respects","w":39.0,"ts":0,"tg":"Espathra","r":["damage_output: 118% HP -> x4.00 (overkill capped)","threat_elimination: guaranteed OHKO on Espathra -> x5.0","turn_order: turn order pos 2/4 (beat 2/3) -> x1.5","opp_protect_recency: target used Protect last turn -> x1.3"]},{"lb":"Last Respects","w":2.95,"ts":1,"tg":"Grimmsnarl","r":["damage_output: 42% HP -> x1.97","turn_order: turn order pos 2/4 (beat 2/3) -> x1.5"]},{"lb":"Switch Ceruledge","w":1.33,"sw":"Ceruledge","r":["switch_tempo: tempo -> x0.8","switch_offense: +67% offense gain -> x1.67"]}],"wall":{"Last Respects>0":39.0,"Last Respects>1":2.95,"+Ceruledge":1.33,"+Decidueye-Hisui":0.25},"ct":"Espathra"}],"ev":[{"o":0,"sd":"opp","a":"Grimmsnarl","mv":"Parting Shot","tg":"Basculegion","h0":1.0},{"o":1,"sd":"opp","a":"Espathra","mv":"Baton Pass","tg":"Espathra","h0":0.57},{"o":2,"sd":"us","a":"Basculegion","mv":"Last Respects","tg":"Eelektross","h0":1.0,"d":0.18},{"o":3,"sd":"us","a":"Kingambit","mv":"Iron Head","tg":"Clefable","h0":1.0,"d":0.66}],"pin":[{"a":"Espathra","df":"Kingambit","mvs":{"Dazzling Gleam":0.266,"Lumina Crash":0.0}},{"a":"Grimmsnarl","df":"Kingambit","mvs":{"Spirit Break":0.243,"Fake Out":0.042}},{"a":"Espathra","df":"Basculegion","mvs":{"Lumina Crash":0.606,"Dazzling Gleam":0.301}},{"a":"Grimmsnarl","df":"Basculegion","mvs":{"Spirit Break":0.394,"Fake Out":0.0}}],"sw":[{"sd":"opp","in":"Clefable","out":"Grimmsnarl"},{"sd":"opp","in":"Eelektross","out":"Espathra"}]},{"n":4,"my":[{"s":"Kingambit","hp":0.957},{"s":"Basculegion","hp":1.0,"b":{"atk":-1,"spa":-1}}],"opp":[{"s":"Eelektross","hp":0.82},{"s":"Clefable","hp":0.58}],"team":[{"s":"Kingambit","hp":0.957},{"s":"Basculegion","hp":1.0},{"s":"Ceruledge","hp":1.0},{"s":"Decidueye-Hisui","hp":1.0}],"dec":[{"sl":0,"ch":"Iron Head","acts":[{"lb":"Iron Head","w":2.23,"ts":1,"tg":"Clefable","r":["damage_output: 85% HP -> x3.49","turn_order: turn order pos 4/4 (beat 0/3) -> x0.75","redirection: pulled to redirector -> 85% dmg -> x0.85"]},{"lb":"Protect","w":1.0},{"lb":"Switch Ceruledge","w":0.8,"sw":"Ceruledge","r":["switch_tempo: tempo -> x0.8","switch_offense: +0% offense gain -> x1.00"]}],"wall":{"Iron Head>1":2.23,"Protect":1.0,"Iron Head>0":0.89,"+Ceruledge":0.8,"+Decidueye-Hisui":0.8,"Kowtow Cleave>0":0.4,"Sucker Punch>0":0.3,"Kowtow Cleave>1":0.21,"Sucker Punch>1":0.17},"ct":"Clefable"},{"sl":1,"ch":"Switch Ceruledge","acts":[{"lb":"Switch Ceruledge","w":4.21,"sw":"Ceruledge","r":["switch_tempo: tempo -> x0.8","switch_offense: +32% offense gain -> x1.32","switch_safety: escapes OHKO -> x4.0"]},{"lb":"Switch Decidueye-Hisui","w":4.08,"sw":"Decidueye-Hisui","r":["switch_tempo: tempo -> x0.8","switch_offense: +27% offense gain -> x1.27","switch_safety: escapes OHKO -> x4.0"]},{"lb":"Last Respects","w":0.53,"ts":0,"tg":"Eelektross","r":["damage_output: 23% HP -> x1.31","turn_order: turn order pos 1/4 (beat 3/3) -> x2.0","redirection: pulled to redirector -> 20% dmg -> x0.20"]}],"wall":{"+Ceruledge":4.21,"+Decidueye-Hisui":4.08,"Last Respects>0":0.53,"Last Respects>1":0.48}}],"ev":[{"o":0,"sd":"opp","a":"Eelektross-Mega","mv":"Flamethrower","tg":"Kingambit","h0":0.957,"d":0.957},{"o":1,"sd":"opp","a":"Clefable","mv":"Psych Up","tg":"Eelektross-Mega","h0":0.82}],"pin":[{"a":"Eelektross-Mega","df":"Kingambit","mvs":{"Flamethrower":0.719,"Thunderbolt":0.537,"Discharge":0.355,"Dragon Pulse":0.168,"Giga Drain":0.149}},{"a":"Clefable","df":"Kingambit","mvs":{"Moonblast":0.322}},{"a":"Eelektross-Mega","df":"Basculegion","mvs":{"Thunderbolt":1.221,"Discharge":0.798,"Giga Drain":0.686,"Dragon Pulse":0.385,"Flamethrower":0.202}},{"a":"Clefable","df":"Basculegion","mvs":{"Moonblast":0.366}}],"res":{"us":["Kingambit"]},"sw":[{"sd":"us","in":"Ceruledge","out":"Basculegion"},{"sd":"us","in":"Basculegion","out":"Kingambit"}]},{"n":5,"my":[{"s":"Basculegion","hp":1.0},{"s":"Ceruledge","hp":1.0}],"opp":[{"s":"Eelektross-Mega","hp":0.82,"mv":["Flamethrower"],"b":{"spa":1}},{"s":"Clefable","hp":0.58,"mv":["Psych Up"]}],"team":[{"s":"Basculegion","hp":1.0},{"s":"Ceruledge","hp":1.0},{"s":"Kingambit","hp":0.0},{"s":"Decidueye-Hisui","hp":1.0}],"dec":[{"sl":0,"ch":"Wave Crash","acts":[{"lb":"Wave Crash","w":4.6,"ts":0,"tg":"Eelektross-Mega","r":["damage_output: 82% HP -> x3.36","turn_order: turn order pos 1/4 (beat 3/3) -> x2.0","redirection: pulled to redirector -> 69% dmg -> x0.69"]},{"lb":"Wave Crash","w":3.97,"ts":1,"tg":"Clefable","r":["damage_output: 69% HP -> x2.90","turn_order: turn order pos 1/4 (beat 3/3) -> x2.0","redirection: pulled to redirector -> 69% dmg -> x0.69"]},{"lb":"Last Respects","w":3.3,"ts":0,"tg":"Eelektross-Mega","r":["damage_output: 69% HP -> x2.90","turn_order: turn order pos 1/4 (beat 3/3) -> x2.0","redirection: pulled to redirector -> 57% dmg -> x0.57"]},{"lb":"Last Respects","w":2.84,"ts":1,"tg":"Clefable","r":["damage_output: 57% HP -> x2.49","turn_order: turn order pos 1/4 (beat 3/3) -> x2.0","redirection: pulled to redirector -> 57% dmg -> x0.57"]}],"wall":{"Wave Crash>0":4.6,"Wave Crash>1":3.97,"Last Respects>0":3.3,"Last Respects>1":2.84,"Psychic Fangs>0":0.74,"Aqua Jet>0":0.71,"Aqua Jet>1":0.65,"Psychic Fangs>1":0.65,"+Decidueye-Hisui":0.24},"ct":"Eelektross-Mega"},{"sl":1,"ch":"Poltergeist","acts":[{"lb":"Poltergeist","w":1.11,"ts":0,"tg":"Eelektross-Mega","r":["damage_output: 55% HP -> x2.41","turn_order: turn order pos 3/4 (beat 1/3) -> x1.0","redirection: pulled to redirector -> 46% dmg -> x0.46"]},{"lb":"Protect","w":1.0},{"lb":"Bitter Blade","w":0.79,"ts":0,"tg":"Eelektross-Mega","r":["damage_output: 45% HP -> x2.07","turn_order: turn order pos 3/4 (beat 1/3) -> x1.0","redirection: pulled to redirector -> 38% dmg -> x0.38"]}],"wall":{"Poltergeist>0":1.11,"Protect":1.0,"Bitter Blade>0":0.79,"Bitter Blade>1":0.69,"+Decidueye-Hisui":0.24,"Poltergeist>1":0.23,"Shadow Sneak>0":0.21,"Shadow Sneak>1":0.19},"ct":"Eelektross-Mega"}],"ev":[{"o":0,"sd":"opp","a":"Clefable","mv":"Protect","tg":"Clefable","h0":0.58},{"o":1,"sd":"opp","a":"Eelektross-Mega","mv":"Discharge","tg":"Ceruledge","h0":1.0,"d":0.718,"z":"protect"},{"o":2,"sd":"us","a":"Ceruledge","mv":"Poltergeist","tg":"Eelektross-Mega","h0":0.82,"d":0.42}],"pin":[{"a":"Eelektross-Mega","df":"Basculegion","mvs":{"Thunderbolt":1.812,"Discharge":1.211,"Giga Drain":1.014,"Dragon Pulse":0.573,"Flamethrower":0.301}},{"a":"Clefable","df":"Basculegion","mvs":{"Moonblast":0.366}},{"a":"Eelektross-Mega","df":"Ceruledge","mvs":{"Thunderbolt":0.787,"Discharge":0.526,"Dragon Pulse":0.496,"Giga Drain":0.22,"Flamethrower":0.0}},{"a":"Clefable","df":"Ceruledge","mvs":{"Moonblast":0.158}}],"res":{"us":["Basculegion"]},"sw":[{"sd":"us","in":"Decidueye-Hisui","out":"Basculegion"}]},{"n":6,"my":[{"s":"Decidueye-Hisui","hp":1.0},{"s":"Ceruledge","hp":0.282}],"opp":[{"s":"Eelektross-Mega","hp":0.4,"mv":["Discharge","Flamethrower"],"b":{"spa":2}},{"s":"Clefable","hp":0.58,"mv":["Protect","Psych Up"]}],"team":[{"s":"Decidueye-Hisui","hp":1.0},{"s":"Ceruledge","hp":0.282},{"s":"Kingambit","hp":0.0},{"s":"Basculegion","hp":0.0}],"dec":[{"sl":0,"ch":"Protect","acts":[{"lb":"Protect","w":7.5,"r":["incoming_ohko: OHKO threat -> x2.5","protect: partner clears slot-0's threat -> x3.0"]},{"lb":"Leaf Blade","w":0.34,"ts":0,"tg":"Eelektross-Mega","r":["damage_output: 103% HP -> x4.00 (overkill capped)","doomed: KO'd before this move lands — undeliverable -> x0.2","turn_order: turn order pos 3/4 (beat 1/3) -> x1.0","redirection: pulled to redirector -> 43% dmg -> x0.43"]},{"lb":"Sucker Punch","w":0.26,"ts":0,"tg":"Eelektross-Mega","r":["damage_output: 54% HP -> x2.39","turn_order: turn order pos 3/4 (beat 1/3) -> x1.0","redirection: pulled to redirector -> 11% dmg -> x0.11"]},{"lb":"Triple Arrows","w":0.07,"ts":1,"tg":"Clefable","r":["damage_output: 21% HP -> x1.24","doomed: KO'd before this move lands — undeliverable -> x0.2","turn_order: turn order pos 3/4 (beat 1/3) -> x1.0","opp_protect_recency: target used Protect last turn -> x1.3","redirection: pulled to redirector -> 21% dmg -> x0.21"]}],"wall":{"Protect":7.5,"Leaf Blade>0":0.34,"Sucker Punch>0":0.26,"Leaf Blade>1":0.22,"Triple Arrows>0":0.17,"Sucker Punch>1":0.13,"Triple Arrows>1":0.07}},{"sl":1,"ch":"Poltergeist","acts":[{"lb":"Poltergeist","w":2.75,"ts":0,"tg":"Eelektross-Mega","r":["damage_output: 112% HP -> x4.00 (overkill capped)","threat_elimination: guaranteed OHKO on Eelektross-Mega -> x5.0","doomed: KO'd before this move lands — undeliverable -> x0.2","turn_order: turn order pos 2/4 (beat 2/3) -> x1.5","redirection: pulled to redirector -> 46% dmg -> x0.46","protect: partner clears slot-0's threat -> x3.0"]},{"lb":"Protect","w":2.5,"r":["incoming_ohko: OHKO threat -> x2.5"]},{"lb":"Shadow Sneak","w":0.52,"ts":0,"tg":"Eelektross-Mega","r":["damage_output: 43% HP -> x1.99","turn_order: turn order pos 2/4 (beat 2/3) -> x1.5","redirection: pulled to redirector -> 17% dmg -> x0.17"]},{"lb":"Bitter Blade","w":0.27,"ts":1,"tg":"Clefable","r":["damage_output: 38% HP -> x1.83","doomed: KO'd before this move lands — undeliverable -> x0.2","turn_order: turn order pos 2/4 (beat 2/3) -> x1.5","opp_protect_recency: target used Protect last turn -> x1.3","redirection: pulled to redirector -> 38% dmg -> x0.38"]}],"wall":{"Poltergeist>0":2.75,"Protect":2.5,"Shadow Sneak>0":0.52,"Bitter Blade>0":0.42,"Shadow Sneak>1":0.38,"Bitter Blade>1":0.27,"Poltergeist>1":0.09},"ct":"Eelektross-Mega"}],"ev":[{"o":0,"sd":"us","a":"Decidueye-Hisui","mv":"Protect","tg":"Decidueye-Hisui","h0":1.0},{"o":1,"sd":"opp","a":"Clefable","mv":"Follow Me","tg":"Clefable","h0":0.58},{"o":2,"sd":"opp","a":"Eelektross-Mega","mv":"Flamethrower","tg":"Decidueye-Hisui","h0":1.0,"z":"protect"},{"o":3,"sd":"us","a":"Ceruledge","mv":"Poltergeist"}],"pin":[{"a":"Eelektross-Mega","df":"Decidueye-Hisui","mvs":{"Flamethrower":1.512,"Dragon Pulse":0.714,"Thunderbolt":0.566,"Discharge":0.375,"Giga Drain":0.312}},{"a":"Clefable","df":"Decidueye-Hisui","mvs":{"Moonblast":0.677}},{"a":"Eelektross-Mega","df":"Ceruledge","mvs":{"Thunderbolt":3.718,"Discharge":2.467,"Dragon Pulse":2.34,"Giga Drain":1.034,"Flamethrower":0.0}},{"a":"Clefable","df":"Ceruledge","mvs":{"Moonblast":0.562}}]},{"n":7,"my":[{"s":"Decidueye-Hisui","hp":1.0},{"s":"Ceruledge","hp":0.282}],"opp":[{"s":"Eelektross-Mega","hp":0.4,"mv":["Discharge","Flamethrower"],"b":{"spa":2}},{"s":"Clefable","hp":0.58,"mv":["Follow Me","Protect","Psych Up"]}],"team":[{"s":"Decidueye-Hisui","hp":1.0},{"s":"Ceruledge","hp":0.282},{"s":"Kingambit","hp":0.0},{"s":"Basculegion","hp":0.0}],"dec":[{"sl":0,"ch":"Protect","acts":[{"lb":"Protect","w":1.5,"r":["incoming_ohko: OHKO threat -> x2.5","consecutive_protect: used Protect last turn -> x0.2","protect: partner clears slot-0's threat -> x3.0"]},{"lb":"Leaf Blade","w":0.34,"ts":0,"tg":"Eelektross-Mega","r":["damage_output: 103% HP -> x4.00 (overkill capped)","doomed: KO'd before this move lands — undeliverable -> x0.2","turn_order: turn order pos 3/4 (beat 1/3) -> x1.0","redirection: pulled to redirector -> 43% dmg -> x0.43"]},{"lb":"Sucker Punch","w":0.26,"ts":0,"tg":"Eelektross-Mega","r":["damage_output: 54% HP -> x2.39","turn_order: turn order pos 3/4 (beat 1/3) -> x1.0","redirection: pulled to redirector -> 11% dmg -> x0.11"]}],"wall":{"Protect":1.5,"Leaf Blade>0":0.34,"Sucker Punch>0":0.26,"Leaf Blade>1":0.17,"Triple Arrows>0":0.17,"Sucker Punch>1":0.1,"Triple Arrows>1":0.05}},{"sl":1,"ch":"Poltergeist","acts":[{"lb":"Poltergeist","w":2.75,"ts":0,"tg":"Eelektross-Mega","r":["damage_output: 112% HP -> x4.00 (overkill capped)","threat_elimination: guaranteed OHKO on Eelektross-Mega -> x5.0","doomed: KO'd before this move lands — undeliverable -> x0.2","turn_order: turn order pos 2/4 (beat 2/3) -> x1.5","redirection: pulled to redirector -> 46% dmg -> x0.46","protect: partner clears slot-0's threat -> x3.0"]},{"lb":"Protect","w":2.5,"r":["incoming_ohko: OHKO threat -> x2.5"]},{"lb":"Shadow Sneak","w":0.52,"ts":0,"tg":"Eelektross-Mega","r":["damage_output: 43% HP -> x1.99","turn_order: turn order pos 2/4 (beat 2/3) -> x1.5","redirection: pulled to redirector -> 17% dmg -> x0.17"]}],"wall":{"Poltergeist>0":2.75,"Protect":2.5,"Shadow Sneak>0":0.52,"Bitter Blade>0":0.42,"Shadow Sneak>1":0.29,"Bitter Blade>1":0.21,"Poltergeist>1":0.07},"ct":"Eelektross-Mega"}],"ev":[{"o":0,"sd":"us","a":"Decidueye-Hisui","mv":"Protect","tg":"Decidueye-Hisui","h0":1.0},{"o":1,"sd":"opp","a":"Clefable","mv":"Follow Me","tg":"Clefable","h0":0.58},{"o":2,"sd":"opp","a":"Eelektross-Mega","mv":"Flamethrower","tg":"Decidueye-Hisui","h0":1.0,"z":"protect"},{"o":3,"sd":"us","a":"Ceruledge","mv":"Poltergeist"}],"pin":[{"a":"Eelektross-Mega","df":"Decidueye-Hisui","mvs":{"Flamethrower":1.512,"Dragon Pulse":0.714,"Thunderbolt":0.566,"Discharge":0.375,"Giga Drain":0.312}},{"a":"Clefable","df":"Decidueye-Hisui","mvs":{"Moonblast":0.677}},{"a":"Eelektross-Mega","df":"Ceruledge","mvs":{"Thunderbolt":3.718,"Discharge":2.467,"Dragon Pulse":2.34,"Giga Drain":1.034,"Flamethrower":0.0}},{"a":"Clefable","df":"Ceruledge","mvs":{"Moonblast":0.562}}]},{"n":8,"my":[{"s":"Decidueye-Hisui","hp":1.0},{"s":"Ceruledge","hp":0.282}],"opp":[{"s":"Eelektross-Mega","hp":0.4,"mv":["Discharge","Flamethrower"],"b":{"spa":2}},{"s":"Clefable","hp":0.58,"mv":["Follow Me","Protect","Psych Up"]}],"team":[{"s":"Decidueye-Hisui","hp":1.0},{"s":"Ceruledge","hp":0.282},{"s":"Kingambit","hp":0.0},{"s":"Basculegion","hp":0.0}],"dec":[{"sl":0,"ch":"Protect","acts":[{"lb":"Protect","w":1.5,"r":["incoming_ohko: OHKO threat -> x2.5","consecutive_protect: used Protect last turn -> x0.2","protect: partner clears slot-0's threat -> x3.0"]},{"lb":"Leaf Blade","w":0.34,"ts":0,"tg":"Eelektross-Mega","r":["damage_output: 103% HP -> x4.00 (overkill capped)","doomed: KO'd before this move lands — undeliverable -> x0.2","turn_order: turn order pos 3/4 (beat 1/3) -> x1.0","redirection: pulled to redirector -> 43% dmg -> x0.43"]},{"lb":"Sucker Punch","w":0.26,"ts":0,"tg":"Eelektross-Mega","r":["damage_output: 54% HP -> x2.39","turn_order: turn order pos 3/4 (beat 1/3) -> x1.0","redirection: pulled to redirector -> 11% dmg -> x0.11"]}],"wall":{"Protect":1.5,"Leaf Blade>0":0.34,"Sucker Punch>0":0.26,"Leaf Blade>1":0.17,"Triple Arrows>0":0.17,"Sucker Punch>1":0.1,"Triple Arrows>1":0.05}},{"sl":1,"ch":"Poltergeist","acts":[{"lb":"Poltergeist","w":2.75,"ts":0,"tg":"Eelektross-Mega","r":["damage_output: 112% HP -> x4.00 (overkill capped)","threat_elimination: guaranteed OHKO on Eelektross-Mega -> x5.0","doomed: KO'd before this move lands — undeliverable -> x0.2","turn_order: turn order pos 2/4 (beat 2/3) -> x1.5","redirection: pulled to redirector -> 46% dmg -> x0.46","protect: partner clears slot-0's threat -> x3.0"]},{"lb":"Protect","w":2.5,"r":["incoming_ohko: OHKO threat -> x2.5"]},{"lb":"Shadow Sneak","w":0.52,"ts":0,"tg":"Eelektross-Mega","r":["damage_output: 43% HP -> x1.99","turn_order: turn order pos 2/4 (beat 2/3) -> x1.5","redirection: pulled to redirector -> 17% dmg -> x0.17"]}],"wall":{"Poltergeist>0":2.75,"Protect":2.5,"Shadow Sneak>0":0.52,"Bitter Blade>0":0.42,"Shadow Sneak>1":0.29,"Bitter Blade>1":0.21,"Poltergeist>1":0.07},"ct":"Eelektross-Mega"}],"ev":[{"o":0,"sd":"us","a":"Decidueye-Hisui","mv":"Protect"},{"o":1,"sd":"opp","a":"Clefable","mv":"Follow Me","tg":"Clefable","h0":0.58},{"o":2,"sd":"opp","a":"Eelektross-Mega","mv":"Flamethrower","tg":"Decidueye-Hisui","h0":1.0,"d":1.0},{"o":3,"sd":"us","a":"Ceruledge","mv":"Poltergeist"}],"pin":[{"a":"Eelektross-Mega","df":"Decidueye-Hisui","mvs":{"Flamethrower":1.512,"Dragon Pulse":0.714,"Thunderbolt":0.566,"Discharge":0.375,"Giga Drain":0.312}},{"a":"Clefable","df":"Decidueye-Hisui","mvs":{"Moonblast":0.677}},{"a":"Eelektross-Mega","df":"Ceruledge","mvs":{"Thunderbolt":3.718,"Discharge":2.467,"Dragon Pulse":2.34,"Giga Drain":1.034,"Flamethrower":0.0}},{"a":"Clefable","df":"Ceruledge","mvs":{"Moonblast":0.562}}],"res":{"us":["Decidueye-Hisui"]}},{"n":9,"my":[{"s":"Decidueye-Hisui","hp":0.0},{"s":"Ceruledge","hp":0.282}],"opp":[{"s":"Eelektross-Mega","hp":0.4,"mv":["Discharge","Flamethrower"],"b":{"spa":3}},{"s":"Clefable","hp":0.58,"mv":["Follow Me","Protect","Psych Up"]}],"team":[{"s":"Decidueye-Hisui","hp":0.0},{"s":"Ceruledge","hp":0.282},{"s":"Kingambit","hp":0.0},{"s":"Basculegion","hp":0.0}],"dec":[{"sl":1,"ch":"Poltergeist","acts":[{"lb":"Poltergeist","w":2.75,"ts":0,"tg":"Eelektross-Mega","r":["damage_output: 112% HP -> x4.00 (overkill capped)","threat_elimination: guaranteed OHKO on Eelektross-Mega -> x5.0","doomed: KO'd before this move lands — undeliverable -> x0.2","turn_order: turn order pos 2/4 (beat 2/3) -> x1.5","redirection: pulled to redirector -> 46% dmg -> x0.46"]},{"lb":"Protect","w":2.5,"r":["incoming_ohko: OHKO threat -> x2.5"]},{"lb":"Shadow Sneak","w":0.52,"ts":0,"tg":"Eelektross-Mega","r":["damage_output: 43% HP -> x1.99","turn_order: turn order pos 2/4 (beat 2/3) -> x1.5","redirection: pulled to redirector -> 17% dmg -> x0.17"]}],"wall":{"Poltergeist>0":2.75,"Protect":2.5,"Shadow Sneak>0":0.52,"Bitter Blade>0":0.42,"Shadow Sneak>1":0.29,"Bitter Blade>1":0.21,"Poltergeist>1":0.07},"ct":"Eelektross-Mega"}],"ev":[{"o":0,"sd":"opp","a":"Clefable","mv":"Follow Me","tg":"Clefable","h0":0.58},{"o":1,"sd":"opp","a":"Eelektross-Mega","mv":"Giga Drain","tg":"Ceruledge","h0":0.282,"d":0.282}],"pin":[{"a":"Eelektross-Mega","df":"Ceruledge","mvs":{"Thunderbolt":4.625,"Discharge":3.101,"Dragon Pulse":2.92,"Giga Drain":1.288,"Flamethrower":0.0}},{"a":"Clefable","df":"Ceruledge","mvs":{"Moonblast":0.562}}],"res":{"us":["Ceruledge"]}}]}