{"id":"battle-gen9championsvgc2026regmb-2640108491","v":"0.31.0","t":"2026-06-27T16:30:50.403115+00:00","outcome":"win","team":"meta-team","team_version":"v7","preview":{"opp":["Blaziken","Kingambit","Aerodactyl","Garchomp","Farigiraf","Gyarados"],"slots":[6,2,1,3],"bring":["Aerodactyl","Kingambit","Lycanroc-Dusk","Basculegion"],"mega":"Aerodactyl"},"final":{"my":[{"s":"Lycanroc-Dusk","hp":1.0,"b":{"atk":-1,"def":-1,"spd":-1}},{"s":"Kingambit","hp":0.121,"b":{"atk":2}}],"opp":[{"s":"Gyarados","hp":0.34,"mv":["Protect"]},{"s":"Kingambit","hp":0.0,"mv":["Kowtow Cleave","Sucker Punch"]}],"team":[{"s":"Lycanroc-Dusk","hp":1.0},{"s":"Kingambit","hp":0.121},{"s":"Basculegion","hp":0.0},{"s":"Aerodactyl-Mega","hp":0.0}]},"opp_formes":["Blaziken","Blaziken-Mega","Garchomp","Gyarados","Kingambit"],"turns":[{"n":1,"my":[{"s":"Aerodactyl","hp":1.0,"b":{"atk":-1}},{"s":"Kingambit","hp":1.0,"b":{"atk":1}}],"opp":[{"s":"Garchomp","hp":1.0},{"s":"Gyarados","hp":1.0}],"team":[{"s":"Aerodactyl","hp":1.0},{"s":"Kingambit","hp":1.0},{"s":"Lycanroc-Dusk","hp":1.0},{"s":"Basculegion","hp":1.0}],"dec":[{"sl":0,"ch":"Ice Fang","acts":[{"lb":"Ice Fang","w":6.88,"ts":0,"tg":"Garchomp","r":["damage_output: 84% HP -> x3.44","turn_order: turn order pos 1/4 (beat 3/3) -> x2.0"]},{"lb":"Dual Wingbeat","w":3.66,"ts":0,"tg":"Garchomp","r":["damage_output: 38% HP -> x1.83","turn_order: turn order pos 1/4 (beat 3/3) -> x2.0"]},{"lb":"Rock Slide","w":3.56,"r":["damage_output: 37% HP -> x1.78","turn_order: turn order pos 1/4 (beat 3/3) -> x2.0"]},{"lb":"Dual Wingbeat","w":3.44,"ts":1,"tg":"Gyarados","r":["damage_output: 35% HP -> x1.72","turn_order: turn order pos 1/4 (beat 3/3) -> x2.0"]}],"wall":{"Ice Fang>0":6.88,"Dual Wingbeat>0":3.66,"Rock Slide":3.56,"Dual Wingbeat>1":3.44,"Ice Fang>1":2.35,"Protect":1.0,"+Lycanroc-Dusk":0.8,"+Basculegion":0.8},"ct":"Garchomp"},{"sl":1,"ch":"Kowtow Cleave","acts":[{"lb":"Kowtow Cleave","w":2.36,"ts":0,"tg":"Garchomp","r":["damage_output: 76% HP -> x3.14","turn_order: turn order pos 4/4 (beat 0/3) -> x0.75"]},{"lb":"Iron Head","w":2.24,"ts":0,"tg":"Garchomp","r":["damage_output: 71% HP -> x2.98","turn_order: turn order pos 4/4 (beat 0/3) -> x0.75"]},{"lb":"Kowtow Cleave","w":2.21,"ts":1,"tg":"Gyarados","r":["damage_output: 70% HP -> x2.95","turn_order: turn order pos 4/4 (beat 0/3) -> x0.75"]},{"lb":"Sucker Punch","w":2.03,"ts":0,"tg":"Garchomp","r":["damage_output: 63% HP -> x2.71","turn_order: turn order pos 4/4 (beat 0/3) -> x0.75"]}],"wall":{"Kowtow Cleave>0":2.36,"Iron Head>0":2.24,"Kowtow Cleave>1":2.21,"Sucker Punch>0":2.03,"Sucker Punch>1":1.89,"Iron Head>1":1.24,"Protect":1.0,"+Basculegion":0.81,"+Lycanroc-Dusk":0.8},"ct":"Garchomp"}],"ev":[{"o":0,"sd":"us","a":"Aerodactyl-Mega","mv":"Ice Fang","tg":"Garchomp","h0":1.0,"d":0.91},{"o":1,"sd":"opp","a":"Garchomp","mv":"Earthquake","tg":"Kingambit","h0":1.0,"d":0.729,"z":"immune"},{"o":2,"sd":"opp","a":"Gyarados","mv":"Waterfall","tg":"Aerodactyl-Mega","h0":1.0,"d":1.0},{"o":3,"sd":"us","a":"Kingambit","mv":"Kowtow Cleave","tg":"Gyarados","h0":1.0,"d":0.66}],"pin":[{"a":"Garchomp","df":"Aerodactyl","mvs":{"Dragon Claw":0.713,"Rock Slide":0.672,"Earthquake":0.0,"Stomping Tantrum":0.0}},{"a":"Gyarados","df":"Aerodactyl","mvs":{"Waterfall":0.884,"Ice Fang":0.483}},{"a":"Garchomp","df":"Kingambit","mvs":{"Earthquake":0.76,"Stomping Tantrum":0.76,"Dragon Claw":0.201,"Rock Slide":0.094}},{"a":"Gyarados","df":"Kingambit","mvs":{"Waterfall":0.255,"Ice Fang":0.067}}],"res":{"us":["Aerodactyl-Mega"],"opp":["Garchomp"]},"sw":[{"sd":"us","in":"Basculegion","out":"Aerodactyl-Mega"},{"sd":"opp","in":"Blaziken","out":"Garchomp"}]},{"n":2,"my":[{"s":"Basculegion","hp":1.0},{"s":"Kingambit","hp":0.271,"b":{"atk":1}}],"opp":[{"s":"Blaziken","hp":1.0},{"s":"Gyarados","hp":0.34,"mv":["Waterfall"]}],"team":[{"s":"Basculegion","hp":1.0},{"s":"Kingambit","hp":0.271},{"s":"Lycanroc-Dusk","hp":1.0},{"s":"Aerodactyl-Mega","hp":0.0}],"dec":[{"sl":0,"ch":"Wave Crash","acts":[{"lb":"Wave Crash","w":77.59,"ts":0,"tg":"Blaziken","r":["damage_output: 207% HP -> x7.76","threat_elimination: guaranteed OHKO on Blaziken -> x5.0","turn_order: turn order pos 1/4 (beat 3/3) -> x2.0"]},{"lb":"Last Respects","w":66.0,"ts":1,"tg":"Gyarados","r":["damage_output: 174% HP -> x6.60","threat_elimination: guaranteed OHKO on Gyarados -> x5.0","turn_order: turn order pos 1/4 (beat 3/3) -> x2.0"]},{"lb":"Wave Crash","w":8.23,"ts":1,"tg":"Gyarados","r":["damage_output: 103% HP -> x4.11","turn_order: turn order pos 1/4 (beat 3/3) -> x2.0"]},{"lb":"Last Respects","w":7.1,"ts":0,"tg":"Blaziken","r":["damage_output: 87% HP -> x3.55","turn_order: turn order pos 1/4 (beat 3/3) -> x2.0"]}],"wall":{"Wave Crash>0":77.59,"Last Respects>1":66.0,"Wave Crash>1":8.23,"Last Respects>0":7.1,"Psychic Fangs>0":6.2,"Psychic Fangs>1":6.16,"Aqua Jet>0":5.95,"Aqua Jet>1":3.53,"+Lycanroc-Dusk":0.8},"ct":"Blaziken"},{"sl":1,"ch":"Sucker Punch","acts":[{"lb":"Sucker Punch","w":72.13,"ts":1,"tg":"Gyarados","r":["damage_output: 169% HP -> x6.41","threat_elimination: guaranteed OHKO on Gyarados -> x5.0","priority_kill: priority move guarantees a kill -> x3.0","turn_order: turn order pos 4/4 (beat 0/3) -> x0.75"]},{"lb":"Kowtow Cleave","w":28.8,"ts":1,"tg":"Gyarados","r":["damage_output: 205% HP -> x7.68","threat_elimination: guaranteed OHKO on Gyarados -> x5.0","turn_order: turn order pos 4/4 (beat 0/3) -> x0.75"]},{"lb":"Iron Head","w":2.91,"ts":1,"tg":"Gyarados","r":["damage_output: 97% HP -> x3.88","turn_order: turn order pos 4/4 (beat 0/3) -> x0.75"]},{"lb":"Kowtow Cleave","w":1.72,"ts":0,"tg":"Blaziken","r":["damage_output: 51% HP -> x2.29","turn_order: turn order pos 4/4 (beat 0/3) -> x0.75"]}],"wall":{"Sucker Punch>1":72.13,"Kowtow Cleave>1":28.8,"Iron Head>1":2.91,"Kowtow Cleave>0":1.72,"Iron Head>0":1.64,"Sucker Punch>0":1.49,"Protect":1.0,"+Lycanroc-Dusk":0.8},"ct":"Gyarados"}],"ev":[{"o":0,"sd":"opp","a":"Blaziken-Mega","mv":"Protect","tg":"Blaziken-Mega","h0":1.0},{"o":1,"sd":"us","a":"Kingambit","mv":"Sucker Punch"},{"o":2,"sd":"us","a":"Basculegion","mv":"Wave Crash","tg":"Blaziken-Mega","h0":1.0,"z":"protect"}],"pin":[{"a":"Blaziken-Mega","df":"Basculegion","mvs":{"Flare Blitz":0.512,"Rock Slide":0.324,"Close Combat":0.0}},{"a":"Gyarados","df":"Basculegion","mvs":{"Waterfall":0.216,"Ice Fang":0.117}},{"a":"Blaziken-Mega","df":"Kingambit","mvs":{"Close Combat":4.394,"Flare Blitz":4.394,"Rock Slide":0.347}},{"a":"Gyarados","df":"Kingambit","mvs":{"Waterfall":0.942,"Ice Fang":0.248}}],"sw":[{"sd":"opp","in":"Kingambit","out":"Gyarados"}]},{"n":3,"my":[{"s":"Basculegion","hp":1.0},{"s":"Kingambit","hp":0.271,"b":{"atk":1}}],"opp":[{"s":"Blaziken-Mega","hp":1.0,"mv":["Protect"],"b":{"spe":1}},{"s":"Kingambit","hp":1.0}],"team":[{"s":"Basculegion","hp":1.0},{"s":"Kingambit","hp":0.271},{"s":"Lycanroc-Dusk","hp":1.0},{"s":"Aerodactyl-Mega","hp":0.0}],"dec":[{"sl":0,"ch":"Wave Crash","acts":[{"lb":"Wave Crash","w":15.13,"ts":0,"tg":"Blaziken-Mega","r":["damage_output: 207% HP -> x7.76","threat_elimination: guaranteed OHKO on Blaziken-Mega -> x5.0","doomed: KO'd before this move lands — undeliverable -> x0.2","turn_order: turn order pos 2/4 (beat 2/3) -> x1.5","opp_protect_recency: target used Protect last turn -> x1.3","protect: partner clears slot-1's threat -> x3.0"]},{"lb":"Switch Lycanroc-Dusk","w":3.2,"sw":"Lycanroc-Dusk","r":["switch_tempo: tempo -> x0.8","switch_offense: +0% offense gain -> x1.00","switch_safety: escapes OHKO -> x4.0"]}],"wall":{"Wave Crash>0":15.13,"+Lycanroc-Dusk":3.2,"Wave Crash>1":0.74},"ct":"Blaziken-Mega"},{"sl":1,"ch":"Switch Lycanroc-Dusk","acts":[{"lb":"Protect","w":7.5,"r":["incoming_ohko: OHKO threat -> x2.5","protect: partner clears slot-1's threat -> x3.0"]},{"lb":"Switch Lycanroc-Dusk","w":4.8,"sw":"Lycanroc-Dusk","r":["switch_tempo: tempo -> x0.8","switch_offense: +50% offense gain -> x1.50","switch_safety: escapes OHKO -> x4.0"]},{"lb":"Sucker Punch","w":2.58,"ts":0,"tg":"Blaziken-Mega","r":["damage_output: 42% HP -> x1.98","turn_order: turn order pos 3/4 (beat 1/3) -> x1.0","opp_protect_recency: target used Protect last turn -> x1.3"]},{"lb":"Sucker Punch","w":1.3,"ts":1,"tg":"Kingambit","r":["damage_output: 23% HP -> x1.30","turn_order: turn order pos 3/4 (beat 1/3) -> x1.0"]},{"lb":"Kowtow Cleave","w":0.6,"ts":0,"tg":"Blaziken-Mega","r":["damage_output: 51% HP -> x2.29","doomed: KO'd before this move lands — undeliverable -> x0.2","turn_order: turn order pos 3/4 (beat 1/3) -> x1.0","opp_protect_recency: target used Protect last turn -> x1.3"]}],"wall":{"+Lycanroc-Dusk":4.8,"Sucker Punch>0":2.58,"Protect":7.5,"Sucker Punch>1":1.3,"Kowtow Cleave>0":0.6,"Iron Head>0":0.57,"Kowtow Cleave>1":0.3,"Iron Head>1":0.28}}],"ev":[{"o":0,"sd":"us","a":"Kingambit","mv":"Protect","tg":"Kingambit","h0":0.271},{"o":1,"sd":"opp","a":"Blaziken-Mega","mv":"Flare Blitz","tg":"Kingambit","h0":0.271,"z":"protect"},{"o":2,"sd":"us","a":"Basculegion","mv":"Wave Crash","tg":"Blaziken-Mega","h0":1.0,"d":1.0},{"o":3,"sd":"opp","a":"Kingambit","mv":"Kowtow Cleave","tg":"Basculegion","h0":0.711,"d":0.711}],"pin":[{"a":"Blaziken-Mega","df":"Basculegion","mvs":{"Flare Blitz":0.512,"Rock Slide":0.324,"Close Combat":0.0}},{"a":"Kingambit","df":"Basculegion","mvs":{"Kowtow Cleave":1.296,"Sucker Punch":1.071,"Iron Head":0.301,"Low Kick":0.0}},{"a":"Blaziken-Mega","df":"Kingambit","mvs":{"Close Combat":4.394,"Flare Blitz":4.394,"Rock Slide":0.347}},{"a":"Kingambit","df":"Kingambit","mvs":{"Low Kick":2.18,"Kowtow Cleave":0.694,"Iron Head":0.644,"Sucker Punch":0.578}}],"res":{"us":["Basculegion"],"opp":["Blaziken-Mega"]},"sw":[{"sd":"opp","in":"Gyarados","out":"Blaziken-Mega"},{"sd":"us","in":"Lycanroc-Dusk","out":"Basculegion"}]},{"n":4,"my":[{"s":"Lycanroc-Dusk","hp":1.0,"b":{"atk":-1}},{"s":"Kingambit","hp":0.271,"b":{"atk":2}}],"opp":[{"s":"Gyarados","hp":0.34},{"s":"Kingambit","hp":1.0,"mv":["Kowtow Cleave"]}],"team":[{"s":"Lycanroc-Dusk","hp":1.0},{"s":"Kingambit","hp":0.271},{"s":"Basculegion","hp":0.0},{"s":"Aerodactyl-Mega","hp":0.0}],"dec":[{"sl":0,"ch":"Accelerock","acts":[{"lb":"Accelerock","w":8.32,"ts":0,"tg":"Gyarados","r":["damage_output: 105% HP -> x4.16","turn_order: turn order pos 1/4 (beat 3/3) -> x2.0"]},{"lb":"Close Combat","w":4.82,"ts":1,"tg":"Kingambit","r":["damage_output: 55% HP -> x2.41","turn_order: turn order pos 1/4 (beat 3/3) -> x2.0"]},{"lb":"Close Combat","w":4.47,"ts":0,"tg":"Gyarados","r":["damage_output: 50% HP -> x2.24","turn_order: turn order pos 1/4 (beat 3/3) -> x2.0"]},{"lb":"Drill Run","w":3.56,"ts":1,"tg":"Kingambit","r":["damage_output: 37% HP -> x1.78","turn_order: turn order pos 1/4 (beat 3/3) -> x2.0"]}],"wall":{"Accelerock>0":8.32,"Close Combat>1":4.82,"Close Combat>0":4.47,"Drill Run>1":3.56,"Accelerock>1":1.47,"Protect":1.0,"Drill Run>0":1.0},"ct":"Gyarados"},{"sl":1,"ch":"Sucker Punch","acts":[{"lb":"Sucker Punch","w":125.74,"ts":0,"tg":"Gyarados","r":["damage_output: 225% HP -> x8.38","threat_elimination: guaranteed OHKO on Gyarados -> x5.0","priority_kill: priority move guarantees a kill -> x3.0","turn_order: turn order pos 3/4 (beat 1/3) -> x1.0"]},{"lb":"Kowtow Cleave","w":50.36,"ts":0,"tg":"Gyarados","r":["damage_output: 273% HP -> x10.07","threat_elimination: guaranteed OHKO on Gyarados -> x5.0","turn_order: turn order pos 3/4 (beat 1/3) -> x1.0"]},{"lb":"Iron Head","w":25.02,"ts":0,"tg":"Gyarados","r":["damage_output: 129% HP -> x5.00","threat_elimination: guaranteed OHKO on Gyarados -> x5.0","turn_order: turn order pos 3/4 (beat 1/3) -> x1.0"]},{"lb":"Kowtow Cleave","w":1.8,"ts":1,"tg":"Kingambit","r":["damage_output: 37% HP -> x1.80","turn_order: turn order pos 3/4 (beat 1/3) -> x1.0"]},{"lb":"Protect","w":0.5,"r":["incoming_ohko: OHKO threat -> x2.5","consecutive_protect: used Protect last turn -> x0.2"]}],"wall":{"Sucker Punch>0":125.74,"Kowtow Cleave>0":50.36,"Iron Head>0":25.02,"Kowtow Cleave>1":1.8,"Iron Head>1":1.72,"Sucker Punch>1":1.58,"Protect":0.5},"ct":"Gyarados"}],"ev":[{"o":0,"sd":"opp","a":"Gyarados","mv":"Protect","tg":"Gyarados","h0":0.34},{"o":1,"sd":"opp","a":"Kingambit","mv":"Sucker Punch","tg":"Kingambit","h0":0.271,"d":0.15},{"o":2,"sd":"us","a":"Kingambit","mv":"Sucker Punch"},{"o":3,"sd":"us","a":"Lycanroc-Dusk","mv":"Close Combat","tg":"Kingambit","h0":1.0,"d":1.0}],"pin":[{"a":"Gyarados","df":"Lycanroc-Dusk","mvs":{"Waterfall":1.139,"Ice Fang":0.312}},{"a":"Kingambit","df":"Lycanroc-Dusk","mvs":{"Iron Head":1.58,"Kowtow Cleave":0.845,"Low Kick":0.796,"Sucker Punch":0.698}},{"a":"Gyarados","df":"Kingambit","mvs":{"Waterfall":0.942,"Ice Fang":0.248}},{"a":"Kingambit","df":"Kingambit","mvs":{"Low Kick":2.18,"Kowtow Cleave":0.694,"Iron Head":0.644,"Sucker Punch":0.578}}],"res":{"opp":["Kingambit"]}},{"n":5,"my":[{"s":"Lycanroc-Dusk","hp":1.0,"b":{"atk":-1,"def":-1,"spd":-1}},{"s":"Kingambit","hp":0.121,"b":{"atk":2}}],"opp":[{"s":"Gyarados","hp":0.34,"mv":["Protect"]},{"s":"Kingambit","hp":0.0,"mv":["Kowtow Cleave","Sucker Punch"]}],"team":[{"s":"Lycanroc-Dusk","hp":1.0},{"s":"Kingambit","hp":0.121},{"s":"Basculegion","hp":0.0},{"s":"Aerodactyl-Mega","hp":0.0}],"dec":[{"sl":0,"ch":"Accelerock","acts":[{"lb":"Accelerock","w":10.82,"ts":0,"tg":"Gyarados","r":["damage_output: 105% HP -> x4.16","turn_order: turn order pos 1/3 (beat 2/2) -> x2.0","opp_protect_recency: target used Protect last turn -> x1.3"]},{"lb":"Close Combat","w":5.81,"ts":0,"tg":"Gyarados","r":["damage_output: 50% HP -> x2.24","turn_order: turn order pos 1/3 (beat 2/2) -> x2.0","opp_protect_recency: target used Protect last turn -> x1.3"]},{"lb":"Drill Run","w":1.3,"ts":0,"tg":"Gyarados","r":["damage_output: 0% HP -> x0.50","turn_order: turn order pos 1/3 (beat 2/2) -> x2.0","opp_protect_recency: target used Protect last turn -> x1.3"]}],"wall":{"Accelerock>0":10.82,"Close Combat>0":5.81,"Drill Run>0":1.3,"Protect":1.0},"ct":"Gyarados"},{"sl":1,"ch":"Sucker Punch","acts":[{"lb":"Sucker Punch","w":163.46,"ts":0,"tg":"Gyarados","r":["damage_output: 225% HP -> x8.38","threat_elimination: guaranteed OHKO on Gyarados -> x5.0","priority_kill: priority move guarantees a kill -> x3.0","turn_order: turn order pos 3/3 (beat 0/2) -> x1.0","opp_protect_recency: target used Protect last turn -> x1.3"]},{"lb":"Kowtow Cleave","w":13.09,"ts":0,"tg":"Gyarados","r":["damage_output: 273% HP -> x10.07","threat_elimination: guaranteed OHKO on Gyarados -> x5.0","doomed: KO'd before this move lands — undeliverable -> x0.2","turn_order: turn order pos 3/3 (beat 0/2) -> x1.0","opp_protect_recency: target used Protect last turn -> x1.3"]},{"lb":"Iron Head","w":6.51,"ts":0,"tg":"Gyarados","r":["damage_output: 129% HP -> x5.00","threat_elimination: guaranteed OHKO on Gyarados -> x5.0","doomed: KO'd before this move lands — undeliverable -> x0.2","turn_order: turn order pos 3/3 (beat 0/2) -> x1.0","opp_protect_recency: target used Protect last turn -> x1.3"]}],"wall":{"Sucker Punch>0":163.46,"Kowtow Cleave>0":13.09,"Iron Head>0":6.51,"Protect":1.0},"ct":"Gyarados"}],"pin":[{"a":"Gyarados","df":"Lycanroc-Dusk","mvs":{"Waterfall":1.703,"Ice Fang":0.466}},{"a":"Gyarados","df":"Kingambit","mvs":{"Waterfall":2.109,"Ice Fang":0.555}}]}]}